README.rst
setup.py
boto_s3_shim/__init__.py
boto_s3_shim.egg-info/PKG-INFO
boto_s3_shim.egg-info/SOURCES.txt
boto_s3_shim.egg-info/dependency_links.txt
boto_s3_shim.egg-info/top_level.txt