Metadata-Version: 1.1
Name: boto-s3-shim
Version: 0.0.2
Summary: Inject an alternative S3 server into any boto-based project
Home-page: http://github.com/grahamc/boto_s3_shim
Author: Graham Christensen
Author-email: graham@grahamc.com
License: MIT
Keywords: boto s3 fakes3
Platform: UNKNOWN
Classifier: Development Status :: 3 - Alpha
Classifier: Topic :: Utilities
Classifier: License :: OSI Approved :: MIT License
Classifier: Operating System :: OS Independent
